configproxy/__init__.py
configproxy/_modidx.py
configproxy/ini.py
confproxy/__init__.py
confproxy/_modidx.py
confproxy/ini.py
confproxy-0.0.1.dist-info/licenses/LICENSE
confproxy-0.0.1.dist-info/METADATA
confproxy-0.0.1.dist-info/WHEEL
confproxy-0.0.1.dist-info/entry_points.txt
confproxy-0.0.1.dist-info/top_level.txt
confproxy-0.0.1.dist-info/RECORD
